mcp_mysql_server/__init__.py
mcp_mysql_server/server.py
tests/__init__.py
tests/test_server.py
mcp_mysql_server_licai_czg_202509111517_9baa6c_202509111516_735609_20250911_e5ceb8-1.0.0.dist-info/LICENSE
mcp_mysql_server_licai_czg_202509111517_9baa6c_202509111516_735609_20250911_e5ceb8-1.0.0.dist-info/METADATA
mcp_mysql_server_licai_czg_202509111517_9baa6c_202509111516_735609_20250911_e5ceb8-1.0.0.dist-info/WHEEL
mcp_mysql_server_licai_czg_202509111517_9baa6c_202509111516_735609_20250911_e5ceb8-1.0.0.dist-info/entry_points.txt
mcp_mysql_server_licai_czg_202509111517_9baa6c_202509111516_735609_20250911_e5ceb8-1.0.0.dist-info/top_level.txt
mcp_mysql_server_licai_czg_202509111517_9baa6c_202509111516_735609_20250911_e5ceb8-1.0.0.dist-info/RECORD
