Metadata-Version: 2.1
Name: mcp-mysql-server-licai-czg-202509111517-9baa6c-202509111516-735609-20250911-e5ceb8
Version: 1.0.0
Summary: A MySQL MCP Server for cross-database queries with Chinese field mapping
Home-page: https://github.com/yourusername/mcp-mysql-server
Author: Your Name
Author-email: your.email@example.com
License: UNKNOWN
Project-URL: Bug Reports, https://github.com/yourusername/mcp-mysql-server/issues
Project-URL: Source, https://github.com/yourusername/mcp-mysql-server
Project-URL: Documentation, https://github.com/yourusername/mcp-mysql-server#readme
Keywords: mcp mysql server database cross-database chinese
Platform: UNKNOWN
Classifier: Development Status :: 4 - Beta
Classifier: Intended Audience :: Developers
Classifier: License :: OSI Approved :: MIT License
Classifier: Operating System :: OS Independent
Classifier: Programming Language :: Python :: 3
Classifier: Programming Language :: Python :: 3.8
Classifier: Programming Language :: Python :: 3.9
Classifier: Programming Language :: Python :: 3.10
Classifier: Programming Language :: Python :: 3.11
Classifier: Programming Language :: Python :: 3.12
Classifier: Topic :: Database
Classifier: Topic :: Software Development :: Libraries :: Python Modules
Requires-Python: >=3.8
License-File: LICENSE
Requires-Dist: mcp>=1.0.0
Requires-Dist: pymysql>=1.1.0
Requires-Dist: cryptography>=41.0.0
Requires-Dist: PyMySQL[rsa]>=1.1.0
